LICENSE
MANIFEST.in
README.rst
setup.py
NewsChimp.egg-info/PKG-INFO
NewsChimp.egg-info/SOURCES.txt
NewsChimp.egg-info/dependency_links.txt
NewsChimp.egg-info/requires.txt
NewsChimp.egg-info/top_level.txt
bin/chimpgen
newschimp/__init__.py
newschimp/cli.py
newschimp/core.py
newschimp/renderer.py
newschimp/sender.py
newschimp/utils.py
newschimp/social/__init__.py
newschimp/social/fb.py
newschimp/social/gg.py
newschimp/social/lanyrd.py