Metadata-Version: 1.1
Name: NewsChimp
Version: 0.1.4
Summary: Newsletter generator for MailChimp
Home-page: https://github.com/sputnikus/newschimp
Author: Martin Putniorz
Author-email: mputniorz@gmail.cpm
License: BSD
Keywords: newsletter,mail,mailchimp
Platform: UNKNOWN
Classifier: Development Status :: 2 - Pre-Alpha
Classifier: Environment :: Console
Classifier: Intended Audience :: Developers
Classifier: License :: OSI Approved :: BSD License
Classifier: Operating System :: POSIX
Classifier: Programming Language :: Python :: 3
Classifier: Topic :: Communications :: Email
